dataprepkit_famt/__init__.py
dataprepkit_famt/module1.py
dataprepkkitt_fatma-3.1.1.dist-info/METADATA
dataprepkkitt_fatma-3.1.1.dist-info/WHEEL
dataprepkkitt_fatma-3.1.1.dist-info/entry_points.txt
dataprepkkitt_fatma-3.1.1.dist-info/top_level.txt
dataprepkkitt_fatma-3.1.1.dist-info/RECORD
